{
  "main": {
    "uz": {
      "identity": {
        "version": {
          "_cldrVersion": "24",
          "_number": "$Revision: 9287 $"
        },
        "generation": {
          "_date": "$Date: 2013-08-28 21:32:04 -0500 (Wed, 28 Aug 2013) $"
        },
        "language": "uz"
      },
      "dates": {
        "timeZoneNames": {
          "hourFormat": "+HH:mm;-HH:mm",
          "gmtFormat": "GMT{0}",
          "gmtZeroFormat": "GMT",
          "regionFormat": "{0} vaqti",
          "regionFormat-type-daylight": "{0} kunduzgi vaqti",
          "regionFormat-type-standard": "{0} standart vaqti",
          "fallbackFormat": "{1} ({0})",
          "zone": {
            "America": {
              "Coral_Harbour": {
                "exemplarCity": "Atikokan"
              },
              "Godthab": {
                "exemplarCity": "Nuuk"
              },
              "Indiana": {
                "Vincennes": {
                  "exemplarCity": "Vincennes, Indiana"
                },
                "Petersburg": {
                  "exemplarCity": "Petersburg, Indiana"
                },
                "Tell_City": {
                  "exemplarCity": "Tell City, Indiana"
                },
                "Knox": {
                  "exemplarCity": "Knox, Indiana"
                },
                "Winamac": {
                  "exemplarCity": "Winamac, Indiana"
                },
                "Marengo": {
                  "exemplarCity": "Marengo, Indiana"
                },
                "Vevay": {
                  "exemplarCity": "Vevay, Indiana"
                }
              },
              "Kentucky": {
                "Monticello": {
                  "exemplarCity": "Monticello, Kentucky"
                }
              },
              "Lower_Princes": {
                "exemplarCity": "Lower Prince's Quarter"
              },
              "North_Dakota": {
                "Beulah": {
                  "exemplarCity": "Beulah, North Dakota"
                },
                "New_Salem": {
                  "exemplarCity": "New Salem, North Dakota"
                },
                "Center": {
                  "exemplarCity": "Center, North Dakota"
                }
              },
              "Scoresbysund": {
                "exemplarCity": "Ittoqqortoormiit"
              },
              "St_Barthelemy": {
                "exemplarCity": "St. Barthelemy"
              },
              "St_Johns": {
                "exemplarCity": "St. John’s"
              },
              "St_Kitts": {
                "exemplarCity": "St. Kitts"
              },
              "St_Lucia": {
                "exemplarCity": "St. Lucia"
              },
              "St_Thomas": {
                "exemplarCity": "St. Thomas"
              },
              "St_Vincent": {
                "exemplarCity": "St. Vincent"
              }
            },
            "Atlantic": {
              "Faeroe": {
                "exemplarCity": "Faroe"
              },
              "St_Helena": {
                "exemplarCity": "St. Helena"
              }
            },
            "Europe": {
              "Dublin": {
                "long": {
                  "daylight": "Irlandiya yozgi vaqti"
                }
              },
              "London": {
                "long": {
                  "daylight": "Britaniya yozgi vaqti"
                }
              }
            },
            "Africa": {
              "Asmera": {
                "exemplarCity": "Asmara"
              }
            },
            "Asia": {
              "Calcutta": {
                "exemplarCity": "Kolkata"
              },
              "Katmandu": {
                "exemplarCity": "Kathmandu"
              },
              "Saigon": {
                "exemplarCity": "Ho Chi Minh"
              },
              "Tashkent": {
                "exemplarCity": "Toshkent"
              }
            },
            "Pacific": {
              "Ponape": {
                "exemplarCity": "Pohnpei"
              },
              "Truk": {
                "exemplarCity": "Chuuk"
              }
            },
            "Antarctica": {
              "DumontDUrville": {
                "exemplarCity": "Dumont d’Urville"
              }
            },
            "Etc": {
              "Unknown": {
                "exemplarCity": "Nomaʼlum"
              }
            }
          },
          "metazone": {
            "Afghanistan": {
              "long": {
                "standard": "Afgʻoniston vaqti"
              }
            },
            "Africa_Central": {
              "long": {
                "standard": "Markaziy Afrika vaqti"
              }
            },
            "Africa_Eastern": {
              "long": {
                "standard": "Sharqiy Afrika vaqti"
              }
            },
            "Africa_Southern": {
              "long": {
                "standard": "Janubiy Afrika vaqti"
              }
            },
            "Africa_Western": {
              "long": {
                "generic": "Gʻarbiy Afrika vaqti",
                "standard": "Gʻarbiy Afrika standart vaqti",
                "daylight": "Gʻarbiy Afrika yozgi vaqti"
              }
            },
            "Alaska": {
              "long": {
                "generic": "Alyaska vaqti",
                "standard": "Alyaska standart vaqti",
                "daylight": "Alyaska kunduzgi vaqti"
              }
            },
            "Amazon": {
              "long": {
                "generic": "Amazonka vaqti",
                "standard": "Amazonka standart vaqti",
                "daylight": "Amazonka yozgi vaqti"
              }
            },
            "America_Central": {
              "long": {
                "generic": "Shimoliy Amerika markaziy vaqti",
                "standard": "Shimoliy Amerika markaziy standart vaqti",
                "daylight": "Shimoliy Amerika markaziy kunduzgi vaqti"
              }
            },
            "America_Eastern": {
              "long": {
                "generic": "Shimoliy Amerika sharqiy vaqti",
                "standard": "Shimoliy Amerika sharqiy standart vaqti",
                "daylight": "Shimoliy Amerika sharqiy kunduzgi vaqti"
              }
            },
            "America_Mountain": {
              "long": {
                "generic": "Shimoliy Amerika togʻ vaqti",
                "standard": "Shimoliy Amerika togʻ standart vaqti",
                "daylight": "Shimoliy Amerika togʻ kunduzgi vaqti"
              }
            },
            "America_Pacific": {
              "long": {
                "generic": "Shimoliy Amerika tinch okeani vaqti",
                "standard": "Shimoliy Amerika tinch okeani standart vaqti",
                "daylight": "Shimoliy Amerika tinch okeani kunduzgi vaqti"
              }
            },
            "Arabian": {
              "long": {
                "generic": "Arabiston vaqti",
                "standard": "Arabiston standart vaqti",
                "daylight": "Arabiston kunduzgi vaqti"
              }
            },
            "Argentina": {
              "long": {
                "generic": "Argentina vaqti",
                "standard": "Argentina standart vaqti",
                "daylight": "Argentina yozgi vaqti"
              }
            },
            "Argentina_Western": {
              "long": {
                "generic": "Gʻarbiy Argentina vaqti",
                "standard": "Gʻarbiy Argentina standart vaqti",
                "daylight": "Gʻarbiy Argentina yozgi vaqti"
              }
            },
            "Armenia": {
              "long": {
                "generic": "Aramniston vaqti",
                "standard": "Armaniston standart vaqti",
                "daylight": "Armaniston yozgi vaqti"
              }
            },
            "Atlantic": {
              "long": {
                "generic": "Atlantika vaqti",
                "standard": "Atlantika standart vaqti",
                "daylight": "Atlantika kunduzgi vaqti"
              }
            },
            "Australia_Central": {
              "long": {
                "generic": "Markaziy Avstraliya vaqti",
                "standard": "Markaziy Avstraliya standart vaqti",
                "daylight": "Markaziy Avstraliya kunduzgi vaqti"
              }
            },
            "Australia_CentralWestern": {
              "long": {
                "generic": "Markaziy Avstraliya Gʻarbiy vaqti",
                "standard": "Markaziy Avstraliya Gʻarbiy standart vaqti",
                "daylight": "Markaziy Avstraliya Gʻarbiy kunduzgi vaqti"
              }
            },
            "Australia_Eastern": {
              "long": {
                "generic": "Sharqiy Avstraliya vaqti",
                "standard": "Sharqiy Avstraliya standart vaqti",
                "daylight": "Sharqiy Avstraliya kunduzgi vaqti"
              }
            },
            "Australia_Western": {
              "long": {
                "generic": "Gʻarbiy Avstraliya vaqti",
                "standard": "Gʻarbiy Avstraliya standart vaqti",
                "daylight": "Gʻarbiy Avstraliya kunduzgi vaqti"
              }
            },
            "Azerbaijan": {
              "long": {
                "generic": "Ozarbayjon vaqti",
                "standard": "Ozarbayjon standart vaqti",
                "daylight": "Ozarbayjon yozgi vaqti"
              }
            },
            "Azores": {
              "long": {
                "generic": "Azor vaqti",
                "standard": "Azor standart vaqti",
                "daylight": "Azor yozgi vaqti"
              }
            },
            "Bangladesh": {
              "long": {
                "generic": "Bangladesh vaqti",
                "standard": "Bangladesh standart vaqti",
                "daylight": "Bangladesh yozgi vaqti"
              }
            },
            "Bhutan": {
              "long": {
                "standard": "Butan vaqti"
              }
            },
            "Bolivia": {
              "long": {
                "standard": "Boliviya vaqti"
              }
            },
            "Brasilia": {
              "long": {
                "generic": "Braziliya vaqti",
                "standard": "Braziliya standart vaqti",
                "daylight": "Braziliya yozgi vaqti"
              }
            },
            "Brunei": {
              "long": {
                "standard": "Bruney Darussalom vaqti"
              }
            },
            "Cape_Verde": {
              "long": {
                "generic": "Kabo-Verde vaqti",
                "standard": "Kabo-Verde standart vaqti",
                "daylight": "Kabo-Verde yozgi vaqti"
              }
            },
            "Chamorro": {
              "long": {
                "standard": "Kamorro vaqti"
              }
            },
            "Chatham": {
              "long": {
                "generic": "Chatxam vaqti",
                "standard": "Chatxam standart vaqti",
                "daylight": "Chatxam kunduzgi vaqti"
              }
            },
            "Chile": {
              "long": {
                "generic": "Chili vaqti",
                "standard": "Chili standart vaqti",
                "daylight": "Chili yozgi vaqti"
              }
            },
            "China": {
              "long": {
                "generic": "Xitoy vaqti",
                "standard": "Xitoy standart vaqti",
                "daylight": "Xitoy kunduzgi vaqti"
              }
            },
            "Choibalsan": {
              "long": {
                "generic": "Choybalsan vaqti",
                "standard": "Choybalsan standart vaqti",
                "daylight": "Choybalsan yozgi vaqti"
              }
            },
            "Christmas": {
              "long": {
                "standard": "Rojdestvo oroli vaqti"
              }
            },
            "Cocos": {
              "long": {
                "standard": "Kokos orollari vaqti"
              }
            },
            "Colombia": {
              "long": {
                "generic": "Kolumbiya vaqti",
                "standard": "Kolumbiya standart vaqti",
                "daylight": "Kolumbiya yozgi vaqti"
              }
            },
            "Cook": {
              "long": {
                "generic": "Kuk orollari vaqti",
                "standard": "Kuk orollari standart vaqti",
                "daylight": "Kuk orollari yarim yozgi vaqti"
              }
            },
            "Cuba": {
              "long": {
                "generic": "Kuba vaqti",
                "standard": "Kuba standart vaqti",
                "daylight": "Kuba kunduzgi vaqti"
              }
            },
            "Davis": {
              "long": {
                "standard": "Devis vaqti"
              }
            },
            "DumontDUrville": {
              "long": {
                "standard": "Dumont-d-Urvil vaqti"
              }
            },
            "East_Timor": {
              "long": {
                "standard": "Sharqiy Timor vaqti"
              }
            },
            "Easter": {
              "long": {
                "generic": "Pasxi Oroli vaqti",
                "standard": "Pasxi oroli standart vaqti",
                "daylight": "Pasxi oroli yozgi vaqti"
              }
            },
            "Ecuador": {
              "long": {
                "standard": "Ekvador vaqti"
              }
            },
            "Europe_Central": {
              "long": {
                "generic": "Markaziy Yevropa vaqti",
                "standard": "Markaziy Yevropa standart vaqti",
                "daylight": "Markaziy Yevropa yozgi vaqti"
              }
            },
            "Europe_Eastern": {
              "long": {
                "generic": "Sharqiy Yevropa vaqti",
                "standard": "Sharqiy Yevropa standart vaqti",
                "daylight": "Sharqiy Yevropa yozgi vaqti"
              }
            },
            "Europe_Western": {
              "long": {
                "generic": "Gʻarbiy Yevropa vaqti",
                "standard": "Gʻarbiy Yevropa standart vaqti",
                "daylight": "Gʻarbiy Yevropa yozgi vaqti"
              }
            },
            "Falkland": {
              "long": {
                "generic": "Folklend orollari vaqti",
                "standard": "Folklend orollari standart vaqti",
                "daylight": "Folklend orollari yozgi vaqti"
              }
            },
            "Fiji": {
              "long": {
                "generic": "Fiji vaqti",
                "standard": "Fiji standart vaqti",
                "daylight": "Fiji yozgi vaqti"
              }
            },
            "French_Guiana": {
              "long": {
                "standard": "Frantsuz Gvianasi vaqti"
              }
            },
            "French_Southern": {
              "long": {
                "standard": "Frantsuz janubiy va Antarktika vaqti"
              }
            },
            "Galapagos": {
              "long": {
                "standard": "Galapagos vaqti"
              }
            },
            "Gambier": {
              "long": {
                "standard": "Gambiyer vaqti"
              }
            },
            "Georgia": {
              "long": {
                "generic": "Gruziya vaqti",
                "standard": "Gruziya standart vaqti",
                "daylight": "Gruziya yozgi vaqti"
              }
            },
            "Gilbert_Islands": {
              "long": {
                "standard": "Gilbert orollari vaqti"
              }
            },
            "GMT": {
              "long": {
                "standard": "Grinvich vaqti"
              }
            },
            "Greenland_Eastern": {
              "long": {
                "generic": "Sharqiy Grenlandiya vaqti",
                "standard": "Sharqiy Grenlandiya standart vaqti",
                "daylight": "Sharqiy Grenlandiya yozgi vaqti"
              }
            },
            "Greenland_Western": {
              "long": {
                "generic": "Gʻarbiy Grenlandiya vaqti",
                "standard": "Gʻarbiy Grenlandiya standart vaqti",
                "daylight": "Gʻarbiy Grenlandiya yozgi vaqti"
              }
            },
            "Gulf": {
              "long": {
                "standard": "Koʻrfaz vaqti"
              }
            },
            "Guyana": {
              "long": {
                "standard": "Gayana vaqti"
              }
            },
            "Hawaii_Aleutian": {
              "long": {
                "generic": "Gavayi-aleut vaqti",
                "standard": "Gavayi-aleut standart vaqti",
                "daylight": "Gavayi-aleut kunduzgi vaqti"
              }
            },
            "Hong_Kong": {
              "long": {
                "generic": "Gonkong vaqti",
                "standard": "Gonkong standart vaqti",
                "daylight": "Gonkong yozgi vaqti"
              }
            },
            "Hovd": {
              "long": {
                "generic": "Xovd vaqti",
                "standard": "Xovd standart vaqti",
                "daylight": "Xovd yozgi vaqti"
              }
            },
            "India": {
              "long": {
                "standard": "Hindiston vaqti"
              }
            },
            "Indian_Ocean": {
              "long": {
                "standard": "Hind okeani vaqti"
              }
            },
            "Indochina": {
              "long": {
                "standard": "Hind-Xitoy vaqti"
              }
            },
            "Indonesia_Central": {
              "long": {
                "standard": "Markaziy Indoneziya vaqti"
              }
            },
            "Indonesia_Eastern": {
              "long": {
                "standard": "Sharqiy Indoneziya vaqti"
              }
            },
            "Indonesia_Western": {
              "long": {
                "standard": "Gʻarbiy Indoneziya vaqti"
              }
            },
            "Iran": {
              "long": {
                "generic": "Eron vaqti",
                "standard": "Eron standart vaqti",
                "daylight": "Eron kunduzgi vaqti"
              }
            },
            "Irkutsk": {
              "long": {
                "generic": "Irkutsk vaqti",
                "standard": "Irkutsk standart vaqti",
                "daylight": "Irkutsk yozgi vaqti"
              }
            },
            "Israel": {
              "long": {
                "generic": "Isroil vaqti",
                "standard": "Isroil standart vaqti",
                "daylight": "Isroil kunduzgi vaqti"
              }
            },
            "Japan": {
              "long": {
                "generic": "Yaponiya vaqti",
                "standard": "Yaponiya standart vaqti",
                "daylight": "Yaponiya kunduzgi vaqti"
              }
            },
            "Kazakhstan_Eastern": {
              "long": {
                "standard": "Sharqiy Qozogʻiston vaqti"
              }
            },
            "Kazakhstan_Western": {
              "long": {
                "standard": "Gʻarbiy Qozogʻiston vaqti"
              }
            },
            "Korea": {
              "long": {
                "generic": "Koreya vaqti",
                "standard": "Koreya standart vaqti",
                "daylight": "Koreya kunduzgi vaqti"
              }
            },
            "Kosrae": {
              "long": {
                "standard": "Kosraye vaqti"
              }
            },
            "Krasnoyarsk": {
              "long": {
                "generic": "Krasnoyarsk vaqti",
                "standard": "Krasnoyarsk standart vaqti",
                "daylight": "Krasnoyarsk yozgi vaqti"
              }
            },
            "Kyrgystan": {
              "long": {
                "standard": "Qirgʻiziston vaqti"
              }
            },
            "Line_Islands": {
              "long": {
                "standard": "Layn orollari vaqti"
              }
            },
            "Lord_Howe": {
              "long": {
                "generic": "Lord Xove vaqti",
                "standard": "Lord Xove standart vaqti",
                "daylight": "Lord Xove kunduzgi vaqti"
              }
            },
            "Macquarie": {
              "long": {
                "standard": "Makvari oroli vaqti"
              }
            },
            "Magadan": {
              "long": {
                "generic": "Magadan vaqti",
                "standard": "Magadan standart vaqti",
                "daylight": "Magadan yozgi vaqti"
              }
            },
            "Malaysia": {
              "long": {
                "standard": "Malayziya vaqti"
              }
            },
            "Maldives": {
              "long": {
                "standard": "Maldiv orollar"
              }
            },
            "Marquesas": {
              "long": {
                "standard": "Markezas vaqti"
              }
            },
            "Marshall_Islands": {
              "long": {
                "standard": "Marshall orollari vaqti"
              }
            },
            "Mauritius": {
              "long": {
                "generic": "Mavrikiy vaqti",
                "standard": "Mavrikiy standart vaqti",
                "daylight": "Mavrikiy yozgi vaqti"
              }
            },
            "Mawson": {
              "long": {
                "standard": "Mouvson vaqti"
              }
            },
            "Mongolia": {
              "long": {
                "generic": "Ulan-Bator vaqti",
                "standard": "Ulan-Bator standart vaqti",
                "daylight": "Ulan-Bator yozgi vaqti"
              }
            },
            "Moscow": {
              "long": {
                "generic": "Moskva vaqti",
                "standard": "Moskva standart vaqti",
                "daylight": "Moskva yozgi vaqti"
              }
            },
            "Myanmar": {
              "long": {
                "standard": "Myanma vaqti"
              }
            },
            "Nauru": {
              "long": {
                "standard": "Nauru vaqti"
              }
            },
            "Nepal": {
              "long": {
                "standard": "Nepal vaqti"
              }
            },
            "New_Caledonia": {
              "long": {
                "generic": "Yangi Kaledoniya vaqti",
                "standard": "Yangi Kaledoniya standart vaqti",
                "daylight": "Yangi Kaledoniya yozgi vaqti"
              }
            },
            "New_Zealand": {
              "long": {
                "generic": "Yangi Zelandiya vaqti",
                "standard": "Yangi Zelandiya standart vaqti",
                "daylight": "Yangi Zelandiya kunduzgi vaqti"
              }
            },
            "Newfoundland": {
              "long": {
                "generic": "Nyufaundlend vaqti",
                "standard": "Nyufaundlend standart vaqti",
                "daylight": "Nyufaundlend kunduzgi vaqti"
              }
            },
            "Niue": {
              "long": {
                "standard": "Niuye vaqti"
              }
            },
            "Norfolk": {
              "long": {
                "standard": "Norfolk oroli vaqti"
              }
            },
            "Noronha": {
              "long": {
                "generic": "Fernando de Noronya vaqti",
                "standard": "Fernando de Noronya standart vaqti",
                "daylight": "Fernando de Noronya yozgi vaqti"
              }
            },
            "Novosibirsk": {
              "long": {
                "generic": "Novosibirsk vaqti",
                "standard": "Novosibirsk standart vaqti",
                "daylight": "Novosibirsk yozgi vaqti"
              }
            },
            "Omsk": {
              "long": {
                "generic": "Omsk vaqti",
                "standard": "Omsk standart vaqti",
                "daylight": "Omsk yozgi vaqti"
              }
            },
            "Pakistan": {
              "long": {
                "generic": "Pokiston vaqti",
                "standard": "Pokiston standart vaqti",
                "daylight": "Pokiston yozgi vaqti"
              }
            },
            "Palau": {
              "long": {
                "standard": "Palau vaqti"
              }
            },
            "Papua_New_Guinea": {
              "long": {
                "standard": "Papua-Yangi Gvineya vaqti"
              }
            },
            "Paraguay": {
              "long": {
                "generic": "Paragvay vaqti",
                "standard": "Paragvay standart vaqti",
                "daylight": "Paragvay yozgi vaqti"
              }
            },
            "Peru": {
              "long": {
                "generic": "Peru vaqti",
                "standard": "Peru standart vaqti",
                "daylight": "Peru yozgi vaqti"
              }
            },
            "Philippines": {
              "long": {
                "generic": "Filippin vaqti",
                "standard": "Filippin standart vaqti",
                "daylight": "Filippin yozgi vaqti"
              }
            },
            "Phoenix_Islands": {
              "long": {
                "standard": "Feniks orollari vaqti"
              }
            },
            "Pierre_Miquelon": {
              "long": {
                "generic": "Sent-Pyer va Mikelon vaqti",
                "standard": "Sent-Pyer va Mikelon standart vaqti",
                "daylight": "Sent-Pyer va Mikelon kunduzgi vaqti"
              }
            },
            "Pitcairn": {
              "long": {
                "standard": "Pitkern vaqti"
              }
            },
            "Ponape": {
              "long": {
                "standard": "Ponape vaqti"
              }
            },
            "Reunion": {
              "long": {
                "standard": "Reyunon vaqti"
              }
            },
            "Rothera": {
              "long": {
                "standard": "Rotera vaqti"
              }
            },
            "Sakhalin": {
              "long": {
                "generic": "Saxalin vaqti",
                "standard": "Saxalin standart vaqti",
                "daylight": "Saxalin yozgi vaqti"
              }
            },
            "Samoa": {
              "long": {
                "generic": "Samoa vaqti",
                "standard": "Samoa standart vaqti",
                "daylight": "Samoa kunduzgi vaqti"
              }
            },
            "Seychelles": {
              "long": {
                "standard": "Seyshel orollari vaqti"
              }
            },
            "Singapore": {
              "long": {
                "standard": "Singapur vaqti"
              }
            },
            "Solomon": {
              "long": {
                "standard": "Solomon orollari vaqti"
              }
            },
            "South_Georgia": {
              "long": {
                "standard": "Janubiy Djordjiya vaqti"
              }
            },
            "Suriname": {
              "long": {
                "standard": "Surinam vaqti"
              }
            },
            "Syowa": {
              "long": {
                "standard": "Sova vaqti"
              }
            },
            "Tahiti": {
              "long": {
                "standard": "Taiti vaqti"
              }
            },
            "Taipei": {
              "long": {
                "generic": "Taypey vaqti",
                "standard": "Taypey standart vaqti",
                "daylight": "Taypey kunduzgi vaqti"
              }
            },
            "Tajikistan": {
              "long": {
                "standard": "Tojikiston vaqti"
              }
            },
            "Tokelau": {
              "long": {
                "standard": "Tokelau vaqti"
              }
            },
            "Tonga": {
              "long": {
                "generic": "Tonga vaqti",
                "standard": "Tonga standart vaqti",
                "daylight": "Tonga yozgi vaqti"
              }
            },
            "Truk": {
              "long": {
                "standard": "Chuuk vaqti"
              }
            },
            "Turkmenistan": {
              "long": {
                "generic": "Turkmaniston vaqti",
                "standard": "Turkmaniston standart vaqti",
                "daylight": "Turkmaniston yozgi vaqti"
              }
            },
            "Tuvalu": {
              "long": {
                "standard": "Tuvalu vaqti"
              }
            },
            "Uruguay": {
              "long": {
                "generic": "Urugvay vaqti",
                "standard": "Urugvay standart vaqti",
                "daylight": "Urugvay yozgi vaqti"
              }
            },
            "Uzbekistan": {
              "long": {
                "generic": "Oʻzbekiston vaqti",
                "standard": "Oʻzbekiston standart vaqti",
                "daylight": "Oʻzbekiston yozgi vaqti"
              }
            },
            "Vanuatu": {
              "long": {
                "generic": "Vanuatu vaqti",
                "standard": "Vanuatu standart vaqti",
                "daylight": "Vanuatu yozgi vaqti"
              }
            },
            "Venezuela": {
              "long": {
                "standard": "Venesuela vaqti"
              }
            },
            "Vladivostok": {
              "long": {
                "generic": "Vladivostok vaqti",
                "standard": "Vladivostok standart vaqti",
                "daylight": "Vladivostok yozgi vaqti"
              }
            },
            "Volgograd": {
              "long": {
                "generic": "Volgograd vaqti",
                "standard": "Volgograd standart vaqti",
                "daylight": "Volgograd yozgi vaqti"
              }
            },
            "Vostok": {
              "long": {
                "standard": "Vostok vaqti"
              }
            },
            "Wake": {
              "long": {
                "standard": "Ueyk oroli vaqti"
              }
            },
            "Wallis": {
              "long": {
                "standard": "Uellis va Futuna vaqti"
              }
            },
            "Yakutsk": {
              "long": {
                "generic": "Yakutsk vaqti",
                "standard": "Yakutsk standart vaqti",
                "daylight": "Yakutsk yozgi vaqti"
              }
            },
            "Yekaterinburg": {
              "long": {
                "generic": "Yekaterinburg vaqti",
                "standard": "Yekaterinburg standart vaqti",
                "daylight": "Yekaterinburg yozgi vaqti"
              }
            }
          }
        }
      }
    }
  }
}
