{
  "main": {
    "os": {
      "identity": {
        "version": {
          "_cldrVersion": "24",
          "_number": "$Revision: 9287 $"
        },
        "generation": {
          "_date": "$Date: 2013-08-28 21:32:04 -0500 (Wed, 28 Aug 2013) $"
        },
        "language": "os"
      },
      "localeDisplayNames": {
        "territories": {
          "001": "Дуне",
          "002": "Африкӕ",
          "009": "Океани",
          "019": "Америкӕ",
          "142": "Ази",
          "150": "Европӕ",
          "BR": "Бразили",
          "CN": "Китай",
          "DE": "Герман",
          "FR": "Франц",
          "GB": "Стыр Британи",
          "GE": "Гуырдзыстон",
          "IN": "Инди",
          "IT": "Итали",
          "JP": "Япон",
          "RU": "Уӕрӕсе",
          "US": "АИШ",
          "ZZ": "Нӕзонгӕ бӕстӕ"
        }
      }
    }
  }
}
