{
  "main": {
    "kl": {
      "identity": {
        "version": {
          "_cldrVersion": "24",
          "_number": "$Revision: 9287 $"
        },
        "generation": {
          "_date": "$Date: 2013-08-28 21:32:04 -0500 (Wed, 28 Aug 2013) $"
        },
        "language": "kl"
      },
      "dates": {
        "timeZoneNames": {
          "hourFormat": "+HH:mm;−HH:mm",
          "gmtFormat": "GMT{0}",
          "gmtZeroFormat": "GMT",
          "regionFormat": "{0}",
          "fallbackFormat": "{0} ({1})",
          "zone": {
            "America": {
              "Scoresbysund": {
                "exemplarCity": "Ittoqqortoormiit"
              },
              "Thule": {
                "exemplarCity": "Qaanaaq"
              }
            },
            "Etc": {
              "Unknown": {
                "exemplarCity": "atorsinnaanngitsoq nalunaaqutaqaqatigiissut"
              }
            }
          }
        }
      }
    }
  }
}
