{
  "main": {
    "bs-Cyrl": {
      "identity": {
        "version": {
          "_cldrVersion": "24",
          "_number": "$Revision: 9287 $"
        },
        "generation": {
          "_date": "$Date: 2013-08-28 21:32:04 -0500 (Wed, 28 Aug 2013) $"
        },
        "language": "bs",
        "script": "Cyrl"
      },
      "dates": {
        "calendars": {
          "hebrew": {
            "months": {
              "format": {
                "wide": {
                  "1": "Тишри",
                  "2": "Хешван",
                  "3": "Кислев",
                  "4": "Тевет",
                  "5": "Шеват",
                  "6": "Адар I",
                  "7": "Адар",
                  "7-yeartype-leap": "Адар II",
                  "8": "Нисан",
                  "9": "Ијар",
                  "10": "Сиван",
                  "11": "Тамуз",
                  "12": "Ав",
                  "13": "Елул"
                }
              }
            }
          }
        }
      }
    }
  }
}
