{
  "main": {
    "ro": {
      "identity": {
        "version": {
          "_cldrVersion": "24",
          "_number": "$Revision: 9287 $"
        },
        "generation": {
          "_date": "$Date: 2013-08-28 21:32:04 -0500 (Wed, 28 Aug 2013) $"
        },
        "language": "ro"
      },
      "localeDisplayNames": {
        "variants": {
          "1901": "ortografie germană tradițională",
          "1994": "ortografie resiană standardizată",
          "1996": "ortografie germană de la 1996",
          "1606NICT": "franceză medievală târzie până la 1606",
          "1694ACAD": "franceză modernă veche",
          "1959ACAD": "belarusă academică",
          "AREVELA": "armeană orientală",
          "AREVMDA": "armeană occidentală",
          "BAKU1926": "alfabet latin altaic unificat",
          "BISKE": "dialect San Giorgio/Bila",
          "BOONT": "boontling",
          "FONIPA": "alfabet fonetic internațional",
          "FONUPA": "alfabet fonetic uralic",
          "KKCOR": "ortografie comuna cornish",
          "LIPAW": "dialect lipovaz din resiană",
          "MONOTON": "monotonică",
          "NEDIS": "dialect Natisone",
          "NJIVA": "dialect Gniva/Njiva",
          "OSOJS": "dialect Oseacco/Osojane",
          "PINYIN": "pinyin",
          "POLYTON": "politonică",
          "POSIX": "informantică",
          "REVISED": "ortografie revizuită",
          "ROZAJ": "dialect resian",
          "SAAHO": "dialect saho",
          "SCOTLAND": "engleză standard scoțiană",
          "SCOUSE": "dialect scouse",
          "SOLBA": "dialet Stolvizza/Solbica",
          "TARASK": "ortografie taraskievica",
          "UCCOR": "ortografie unificată cornish",
          "UCRCOR": "ortografie revizuită unificată cornish",
          "VALENCIA": "valenciană",
          "WADEGILE": "Wade-Giles"
        }
      }
    }
  }
}
